abstract_paths/__init__.py
abstract_paths/abstractFileImporter.py
abstract_paths/content_utils/__init__.py
abstract_paths/content_utils/diff_engine.py
abstract_paths/content_utils/diff_utils.py
abstract_paths/content_utils/file_utils.py
abstract_paths/content_utils/find_content.py
abstract_paths/content_utils/imports.py
abstract_paths/content_utils/backs/__init__.py
abstract_paths/content_utils/backs/diff_engine.py
abstract_paths/content_utils/backs/diff_utils.py
abstract_paths/content_utils/backs/file_utils.py
abstract_paths/content_utils/backs/find_content.py
abstract_paths/content_utils/backs/imports.py
abstract_paths/file_filtering/__init__.py
abstract_paths/file_filtering/file_filters.py
abstract_paths/file_filtering/filter_params.py
abstract_paths/file_filtering/imports.py
abstract_paths/file_filtering/req.py
abstract_paths/file_handlers/__init__.py
abstract_paths/file_handlers/directory_reader.py
abstract_paths/file_handlers/file_readers.py
abstract_paths/file_handlers/imports.py
abstract_paths/file_handlers/path_handlers.py
abstract_paths/file_handlers/pdf_utils.py
abstract_paths/finderTab/__init__.py
abstract_paths/finderTab/launch_finder_console.py
abstract_paths/finderTab/main.py
abstract_paths/finderTab/src/__init__.py
abstract_paths/finderTab/src/get_all_imps.py
abstract_paths/finderTab/src/launch_finder_console.py
abstract_paths/finderTab/src/main.py
abstract_paths/finderTab/src/imports/__init__.py
abstract_paths/finderTab/src/imports/functions.py
abstract_paths/finderTab/src/imports/imports.py
abstract_paths/finderTab/src/imports/share_utils/__init__.py
abstract_paths/finderTab/src/imports/share_utils/functions.py
abstract_paths/finderTab/src/imports/share_utils/imports.py
abstract_paths/finderTab/src/imports/share_utils/initFuncs.py
abstract_paths/finderTab/src/imports/share_utils/shared/__init__.py
abstract_paths/finderTab/src/imports/share_utils/shared/imports.py
abstract_paths/finderTab/src/imports/share_utils/shared/inputs.py
abstract_paths-0.0.0.189.dist-info/METADATA
abstract_paths-0.0.0.189.dist-info/WHEEL
abstract_paths-0.0.0.189.dist-info/top_level.txt
abstract_paths-0.0.0.189.dist-info/RECORD
